p2d/__init__.py
p2d/__main__.py
p2d/_version.py
p2d/cli.py
p2d/contest.py
p2d/models.py
p2d/p2d.py
p2d/utils.py
p2d/testlib/LICENSE
p2d/testlib/testlib.h
rimuruchan_p2d-0.4.3.dist-info/METADATA
rimuruchan_p2d-0.4.3.dist-info/WHEEL
rimuruchan_p2d-0.4.3.dist-info/entry_points.txt
rimuruchan_p2d-0.4.3.dist-info/licenses/LICENSE
rimuruchan_p2d-0.4.3.dist-info/RECORD
