Metadata-Version: 2.4
Name: rimuruchan-p2d
Version: 0.4.3
Summary: Simple python script converting polygon package to domjudge(kattis) package
Project-URL: homepage, https://github.com/RimuruChan/Polygon2Domjudge
Project-URL: documentation, https://github.com/RimuruChan/Polygon2Domjudge
Project-URL: repository, https://github.com/RimuruChan/Polygon2Domjudge
Author-email: cubercsl <hi@cubercsl.site>, rimuruchan <RealSprite233@outlook.com>
Maintainer-email: rimuruchan <RealSprite233@outlook.com>
License-Expression: MIT
License-File: LICENSE
Keywords: Codeforces,DOMjudge,Kattis,Polygon
Classifier: Programming Language :: Python :: 3
Classifier: Programming Language :: Python :: 3.10
Classifier: Programming Language :: Python :: 3.11
Classifier: Programming Language :: Python :: 3.12
Classifier: Programming Language :: Python :: 3.13
Classifier: Topic :: Software Development :: Build Tools
Classifier: Topic :: Software Development :: Libraries :: Python Modules
Requires-Python: >=3.10
Requires-Dist: deepmerge>=2.0
Requires-Dist: pydantic>=2.10.6
Requires-Dist: pyyaml>=6.0.2
Requires-Dist: rich>=13.9.4
Requires-Dist: tomli>=2.0.1; python_version < '3.11'
Requires-Dist: typer-slim[standard]>=0.12.5
